{"nbPlayers": 8, "duels": [], "isFinished": true, "podium": [{"name": "Lexzero2", "flair": "smileys.skull-and-crossbones", "rank": 1, "rating": 1914, "score": 44, "nb": {"game": 18, "berserk": 0, "win": 15}, "performance": 2167}, {"name": "spicypearl8", "rank": 2, "rating": 1806, "score": 32, "nb": {"game": 25, "berserk": 0, "win": 14}, "performance": 1916}, {"name": "A-king", "flair": "smileys.clown-face", "rank": 3, "rating": 1709, "score": 12, "nb": {"game": 9, "berserk": 0, "win": 5}, "performance": 1913}], "pairingsClosed": true, "stats": {"moves": 2036, "averageRating": 1806, "berserks": 0, "blackWins": 25, "games": 45, "draws": 0, "whiteWins": 20}, "standing": {"page": 1, "players": [{"name": "Lexzero2", "flair": "smileys.skull-and-crossbones", "rank": 1, "rating": 1914, "score": 44, "sheet": {"scores": "442204442204422022", "fire": true}}, {"name": "spicypearl8", "rank": 2, "rating": 1806, "score": 32, "sheet": {"scores": "2022020022020000442202022"}}, {"name": "A-king", "flair": "smileys.clown-face", "rank": 3, "rating": 1709, "score": 12, "sheet": {"scores": "422020002", "fire": true}}, {"name": "BabyDee", "rank": 4, "rating": 1931, "score": 12, "sheet": {"scores": "0200000422002"}}, {"name": "b4elma", "rank": 5, "rating": 1935, "score": 10, "sheet": {"scores": "002000220220"}}, {"name": "genuine99", "rank": 6, "rating": 1672, "score": 2, "sheet": {"scores": "0002000000"}}, {"name": "Dbosman", "rank": 7, "rating": 1644, "score": 0, "sheet": {"scores": "0"}}, {"name": "OvergiftedLight", "flair": "smileys.winking-face-with-tongue", "rank": 8, "rating": 1839, "score": 0, "sheet": {"scores": "00"}}]}, "id": "gQxM15K8", "createdBy": "bayormiller_cno", "startsAt": "2025-05-09T19:00:00Z", "system": "arena", "fullName": "Friday CNO Crazyhouse Arena", "minutes": 90, "perf": {"key": "crazyhouse", "name": "Crazyhouse"}, "clock": {"limit": 60, "increment": 0}, "variant": "crazyhouse", "rated": true, "berserkable": true, "verdicts": {"list": [{"condition": "Rated \u2264 2000 in Crazyhouse for the last week", "verdict": "ok"}], "accepted": true}, "description": "1st - N1,000\r\n2nd - N500", "maxRating": {"rating": 2000}, "players": [{"name": "Lexzero2", "flair": "smileys.skull-and-crossbones", "rank": 1, "rating": 1914, "score": 44, "sheet": {"scores": "442204442204422022", "fire": true}}, {"name": "spicypearl8", "rank": 2, "rating": 1806, "score": 32, "sheet": {"scores": "2022020022020000442202022"}}, {"name": "A-king", "flair": "smileys.clown-face", "rank": 3, "rating": 1709, "score": 12, "sheet": {"scores": "422020002", "fire": true}}, {"name": "BabyDee", "rank": 4, "rating": 1931, "score": 12, "sheet": {"scores": "0200000422002"}}, {"name": "b4elma", "rank": 5, "rating": 1935, "score": 10, "sheet": {"scores": "002000220220"}}, {"name": "genuine99", "rank": 6, "rating": 1672, "score": 2, "sheet": {"scores": "0002000000"}}, {"name": "Dbosman", "rank": 7, "rating": 1644, "score": 0, "sheet": {"scores": "0"}}, {"name": "OvergiftedLight", "flair": "smileys.winking-face-with-tongue", "rank": 8, "rating": 1839, "score": 0, "sheet": {"scores": "00"}}]}